{
    "posts": [
        {
            "title": "Sobre os f\u00e1rmacos de base natural, a hemi-s\u00edntese, e o rumo da ind\u00fastria farmac\u00eautica",
            "selftext": "",
            "subreddit": "Blogue_Eng_Quimica",
            "topic": "ciencia",
            "id": "fhpdx7",
            "num_comments": 0
        },
        {
            "title": "Sobre a ind\u00fastria qu\u00edmica italiana: dimens\u00e3o, setores de atividade, geografia, e a Federchimica, a associa\u00e7\u00e3o que a representa",
            "selftext": "",
            "subreddit": "Blogue_Eng_Quimica",
            "topic": "ciencia",
            "id": "fgec91",
            "num_comments": 0
        },
        {
            "title": "Revista semanal de imprensa (BEQ.2020.6): hidrog\u00e9nio anti-NOx, eletricidade na humidade, nova tinta 'verde' da Barbot, Austr\u00e1lia valoriza batatas pelo amido",
            "selftext": "",
            "subreddit": "Blogue_Eng_Quimica",
            "topic": "ciencia",
            "id": "febjzo",
            "num_comments": 0
        },
        {
            "title": "Sobre o surgimento dos aerog\u00e9is, as suas aplica\u00e7\u00f5es e funcionalidades, e a elevada perspetiva de mercado",
            "selftext": "",
            "subreddit": "Blogue_Eng_Quimica",
            "topic": "ciencia",
            "id": "fduay4",
            "num_comments": 0
        },
        {
            "title": "Produto BEQ do m\u00eas (03/2020): copo The Right Cup e a proposta de beber \u00e1gua fazendo o c\u00e9rebro acreditar que se ingere um sumo frutado e doce",
            "selftext": "",
            "subreddit": "Blogue_Eng_Quimica",
            "topic": "ciencia",
            "id": "fd2ot8",
            "num_comments": 0
        },
        {
            "title": "Sobre o uso de querosene na avia\u00e7\u00e3o, e as suas vantagens e desvantagens em compara\u00e7\u00e3o com outros combust\u00edveis",
            "selftext": "",
            "subreddit": "Blogue_Eng_Quimica",
            "topic": "ciencia",
            "id": "fckjuc",
            "num_comments": 0
        },
        {
            "title": "Sobre as m\u00e1scaras cir\u00fargicas e a sua utiliza\u00e7\u00e3o para conter epidemias v\u00edricas, e os solventes conhecidos para a inativa\u00e7\u00e3o de v\u00edrus",
            "selftext": "",
            "subreddit": "Blogue_Eng_Quimica",
            "topic": "ciencia",
            "id": "fa2lyy",
            "num_comments": 0
        },
        {
            "title": "Coluna 'Ver para Crer' (BEQ.2020.5): a resist\u00eancia do cobre a campos magn\u00e9ticos, apesar de n\u00e3o ter propriedades magn\u00e9ticas",
            "selftext": "",
            "subreddit": "Blogue_Eng_Quimica",
            "topic": "ciencia",
            "id": "f792sw",
            "num_comments": 0
        },
        {
            "title": "Sobre o custo econ\u00f3mico da corros\u00e3o na ind\u00fastria petrol\u00edfera, e a especificidade da corros\u00e3o sour nas explora\u00e7\u00f5es de g\u00e1s e petr\u00f3leo offshore",
            "selftext": "",
            "subreddit": "Blogue_Eng_Quimica",
            "topic": "ciencia",
            "id": "f2ovwe",
            "num_comments": 0
        },
        {
            "title": "Coluna 'Ver para Crer' (BEQ.2020.4): pist\u00e3o de fogo, um mecanismo conhecido h\u00e1 mil\u00e9nios e que obedece ao mesmo princ\u00edpio dos motores a diesel",
            "selftext": "",
            "subreddit": "Blogue_Eng_Quimica",
            "topic": "ciencia",
            "id": "f1o46h",
            "num_comments": 0
        },
        {
            "title": "Sobre o mercado europeu de pl\u00e1sticos, a problem\u00e1tica gest\u00e3o deste tipo de res\u00edduos, e as medidas em marcha para fomentar a reciclagem destes recursos",
            "selftext": "",
            "subreddit": "Blogue_Eng_Quimica",
            "topic": "ciencia",
            "id": "f0ae4b",
            "num_comments": 0
        },
        {
            "title": "Revista semanal de imprensa (BEQ.2020.4): Frulact vendida, Nestl\u00e9 quer pl\u00e1sticos reciclados, futuro limpo s\u00f3 com minerais, e o emprego dos eng\u00bas portugueses",
            "selftext": "",
            "subreddit": "Blogue_Eng_Quimica",
            "topic": "ciencia",
            "id": "ezr804",
            "num_comments": 0
        },
        {
            "title": "Produto BEQ do m\u00eas (02/2020): turbina port\u00e1til WaterLily, e carregamentos el\u00e9tricos de gadgets \u00e0 dist\u00e2ncia de um rio",
            "selftext": "",
            "subreddit": "Blogue_Eng_Quimica",
            "topic": "ciencia",
            "id": "eyyqh4",
            "num_comments": 0
        },
        {
            "title": "Sobre a utiliza\u00e7\u00e3o de ceras de deslizamento em skis com vista a melhorias de desempenho, e as contrapartidas ambientais e de sa\u00fade associadas",
            "selftext": "",
            "subreddit": "Blogue_Eng_Quimica",
            "topic": "ciencia",
            "id": "eyaenv",
            "num_comments": 0
        },
        {
            "title": "Coluna 'Ver para Crer' (BEQ.2020.3): interior de turbina a vapor de 1400 MW de pot\u00eancia vista \u00e0 escala humana",
            "selftext": "",
            "subreddit": "Blogue_Eng_Quimica",
            "topic": "ciencia",
            "id": "ex805f",
            "num_comments": 0
        },
        {
            "title": "Revista semanal de imprensa (BEQ.2020.3): descarboniza\u00e7\u00e3o lenta, entrevista a duas eng\u00aa qu\u00edmicas, e \u00e1gua da torneira cancer\u00edgena",
            "selftext": "",
            "subreddit": "Blogue_Eng_Quimica",
            "topic": "ciencia",
            "id": "ewapew",
            "num_comments": 0
        },
        {
            "title": "Sobre o sal\u00e1rio dos engenheiros qu\u00edmicos nos EUA em 2018, e a sua posi\u00e7\u00e3o relativamente a outras ocupa\u00e7\u00f5es profissionais",
            "selftext": "",
            "subreddit": "Blogue_Eng_Quimica",
            "topic": "ciencia",
            "id": "evc6oy",
            "num_comments": 0
        },
        {
            "title": "Sobre quatro aquisi\u00e7\u00f5es da DuPont em 2019 com vista a expandir o portf\u00f3lio de tecnologias de purifica\u00e7\u00e3o e separa\u00e7\u00e3o de \u00e1gua",
            "selftext": "",
            "subreddit": "Blogue_Eng_Quimica",
            "topic": "ciencia",
            "id": "esaw3z",
            "num_comments": 0
        },
        {
            "title": "Coluna 'Ver para Crer' (BEQ.2020.2): incendiando papel com vapor de \u00e1gua sobreaquecido",
            "selftext": "",
            "subreddit": "Blogue_Eng_Quimica",
            "topic": "ciencia",
            "id": "ertgao",
            "num_comments": 0
        },
        {
            "title": "Revista semanal de imprensa (BEQ.2020.2): baterias a durar 5 dias, energia solar a durar 18 anos, vem a\u00ed ainda mais petr\u00f3leo, e futuro da Sonangol",
            "selftext": "",
            "subreddit": "Blogue_Eng_Quimica",
            "topic": "ciencia",
            "id": "ercz4j",
            "num_comments": 0
        },
        {
            "title": "Sobre a decadente ind\u00fastria qu\u00edmica da Coreia do Norte, e a propaganda do l\u00edder Kim Jong Un apesar dos permanentes entraves cient\u00edficos e tecnol\u00f3gicos",
            "selftext": "",
            "subreddit": "Blogue_Eng_Quimica",
            "topic": "ciencia",
            "id": "epibhp",
            "num_comments": 0
        },
        {
            "title": "Produto BEQ do m\u00eas (01/2020): alcool\u00edmetro/baf\u00f4metro port\u00e1til BACtrack Go, para controlar preventivamente o \u00e1lcool no sangue",
            "selftext": "",
            "subreddit": "Blogue_Eng_Quimica",
            "topic": "ciencia",
            "id": "eok3dr",
            "num_comments": 0
        },
        {
            "title": "Coluna 'Ver para Crer' (BEQ.2020.1): os diferentes tipos de bomba e seus modos de opera\u00e7\u00e3o",
            "selftext": "",
            "subreddit": "Blogue_Eng_Quimica",
            "topic": "ciencia",
            "id": "eo28wv",
            "num_comments": 0
        },
        {
            "title": "Sobre o surgimento da quimioterapia e dos tratamentos oncol\u00f3gicos, exemplos de f\u00e1rmacos, e tend\u00eancias sobre a ind\u00fastria mundial destes compostos qu\u00edmicos",
            "selftext": "",
            "subreddit": "Blogue_Eng_Quimica",
            "topic": "ciencia",
            "id": "en86rr",
            "num_comments": 0
        },
        {
            "title": "Revista semanal de imprensa (BEQ.2020.1): hidrog\u00e9nio luso, impacto dos biocombust\u00edveis, universidades sauditas, fus\u00f5es nos pesticidas chineses",
            "selftext": "",
            "subreddit": "Blogue_Eng_Quimica",
            "topic": "ciencia",
            "id": "elqxxh",
            "num_comments": 0
        },
        {
            "title": "Sobre a (inesperada) presen\u00e7a de empresas da ind\u00fastria qu\u00edmica e petroqu\u00edmica nos patroc\u00ednios a clubes de futebol, incluindo em Portugal e Brasil",
            "selftext": "",
            "subreddit": "Blogue_Eng_Quimica",
            "topic": "ciencia",
            "id": "e9a7j5",
            "num_comments": 0
        },
        {
            "title": "Revista semanal de imprensa (BEQ.2019.30): novo CEO da Navigator, sustentabilidade no t\u00eaxtil, mercado mundial de frag\u00e2ncias, inova\u00e7\u00e3o em baterias de l\u00edtio",
            "selftext": "",
            "subreddit": "Blogue_Eng_Quimica",
            "topic": "ciencia",
            "id": "e8r0ij",
            "num_comments": 0
        },
        {
            "title": "Sobre a Funda\u00e7\u00e3o Gulbenkian como herdeira dos ativos de Calouste Gulbenkian no setor do petr\u00f3leo, e a desvincula\u00e7\u00e3o desta do investimento em petr\u00f3leo e g\u00e1s",
            "selftext": "",
            "subreddit": "Blogue_Eng_Quimica",
            "topic": "ciencia",
            "id": "e88ftd",
            "num_comments": 0
        },
        {
            "title": "Coluna 'Ver para Crer' (BEQ.2019.32): as etapas envolvidas na reciclagem de dispositivos eletr\u00f3nicos",
            "selftext": "",
            "subreddit": "Blogue_Eng_Quimica",
            "topic": "ciencia",
            "id": "e6wwz4",
            "num_comments": 0
        },
        {
            "title": "Sobre a hist\u00f3rica da ind\u00fastria (petro)qu\u00edmica no estado norte-americano do Louisiana, o crescente emprego, e os desafios ambientais da sua intensidade industrial",
            "selftext": "",
            "subreddit": "Blogue_Eng_Quimica",
            "topic": "ciencia",
            "id": "e5y7hr",
            "num_comments": 0
        },
        {
            "title": "Sobre o novo pipeline russo 'Power of Siberia', no valor de 55 mil milh\u00f5es de d\u00f3lares, com vista a abastecer 9,5% do g\u00e1s natural consumido na China",
            "selftext": "",
            "subreddit": "Blogue_Eng_Quimica",
            "topic": "ciencia",
            "id": "e5fbjj",
            "num_comments": 0
        },
        {
            "title": "Revista semanal de imprensa (BEQ.2019.29): carv\u00e3o polui desde 1960, ONU quer reduzir emiss\u00f5es, \"imperial de caf\u00e9\" lan\u00e7ada, e g\u00e1s natural ajuda \u00e0 descarboniza\u00e7\u00e3o",
            "selftext": "",
            "subreddit": "Blogue_Eng_Quimica",
            "topic": "ciencia",
            "id": "e3f2v1",
            "num_comments": 0
        },
        {
            "title": "Coluna 'Ver para Crer' (BEQ.2019.31): removendo \u00f3leo de um motor com recurso a feixes laser",
            "selftext": "",
            "subreddit": "Blogue_Eng_Quimica",
            "topic": "ciencia",
            "id": "e2e53l",
            "num_comments": 0
        },
        {
            "title": "Sobre o concurso para otimizar a performance de uma unidade da refinaria de Sines, vencido por data scientists das Universidades de Aveiro e de Liverpool",
            "selftext": "",
            "subreddit": "Blogue_Eng_Quimica",
            "topic": "ciencia",
            "id": "e1wcgl",
            "num_comments": 0
        },
        {
            "title": "Sobre o emprego e empregabilidade de rec\u00e9m-graduados em eng\u00aa qu\u00edmica: perspectivas para refletir e expandir horizontes",
            "selftext": "",
            "subreddit": "Blogue_Eng_Quimica",
            "topic": "ciencia",
            "id": "e1huou",
            "num_comments": 0
        },
        {
            "title": "Revista semanal de imprensa (BEQ.2019.28): refinaria de l\u00edtio e f\u00e1brica de hidrog\u00e9nio na agenda pol\u00edtica, aterro sanit\u00e1rio saturado, e Saudi Aramco \u00e0 venda",
            "selftext": "",
            "subreddit": "Blogue_Eng_Quimica",
            "topic": "ciencia",
            "id": "dzjt26",
            "num_comments": 0
        },
        {
            "title": "Sobre a produ\u00e7\u00e3o de hidrog\u00e9nio a partir de energia solar: perspetivas t\u00e9cnicas e econ\u00f3micas, e sinergias com os pipelines de g\u00e1s natural",
            "selftext": "",
            "subreddit": "Blogue_Eng_Quimica",
            "topic": "ciencia",
            "id": "dz0foa",
            "num_comments": 0
        },
        {
            "title": "Coluna 'Ver para Crer' (BEQ.2019.30): resumo das v\u00e1rias rea\u00e7\u00f5es qu\u00edmicas pass\u00edveis de acontecer a partir de benzeno",
            "selftext": "",
            "subreddit": "Blogue_Eng_Quimica",
            "topic": "ciencia",
            "id": "dys27v",
            "num_comments": 0
        },
        {
            "title": "Sobre o sistema de mapeamento de gases LiDAR\u2122, e o crescimento de 56% do mercado de drones para fotografia a\u00e9rea e sensoriamento remoto at\u00e9 2025",
            "selftext": "",
            "subreddit": "Blogue_Eng_Quimica",
            "topic": "ciencia",
            "id": "dyno0q",
            "num_comments": 0
        },
        {
            "title": "Revista semanal de imprensa (BEQ.2019.27): spin-off de microfluidos premiada, Continental refor\u00e7a no Porto, monop\u00f3lio no g\u00e1s natural, e (h)umidade nos f\u00e1rmacos",
            "selftext": "",
            "subreddit": "Blogue_Eng_Quimica",
            "topic": "ciencia",
            "id": "dynnjl",
            "num_comments": 0
        },
        {
            "title": "Sobre a expans\u00e3o do mercado mundial de baterias l\u00edtio, e o papel da Europa e de Portugal na cadeia de valor destes produtos",
            "selftext": "",
            "subreddit": "Blogue_Eng_Quimica",
            "topic": "ciencia",
            "id": "dynn6r",
            "num_comments": 0
        },
        {
            "title": "Blogue_Eng_Quimica has been created",
            "selftext": "Divulga\u00e7\u00e3o de Eng\u00aa Qu\u00edmica em l\u00edngua portuguesa.",
            "subreddit": "Blogue_Eng_Quimica",
            "topic": "ciencia",
            "id": "dyni10",
            "num_comments": 0
        }
    ]
}